{"cameraMode":{"drawMode":0,"name":"Shaded","section":"Shading Mode"},"sceneLighting":false,"audioPlay":false,"sceneViewState":{"m_AlwaysRefresh":false,"showFog":false,"showSkybox":false,"showFlares":false,"showImageEffects":false,"showParticleSystems":false,"showVisualEffectGraphs":true,"m_FxEnabled":true},"in2DMode":false,"pivot":{"x":1.4267024993896485,"y":2.1361243724823,"z":-0.6476121544837952},"rotation":{"x":0.05478617176413536,"y":0.7911642789840698,"z":-0.07164136320352555,"w":0.6049462556838989},"size":2.08773136138916,"orthographic":false}